suprsend/__init__.py
suprsend/attachment.py
suprsend/brand.py
suprsend/bulk_response.py
suprsend/constants.py
suprsend/event.py
suprsend/events_bulk.py
suprsend/exception.py
suprsend/object_edit.py
suprsend/object_edit_internal_helper.py
suprsend/objects_api.py
suprsend/request_log.py
suprsend/request_schema.py
suprsend/sdkinstance.py
suprsend/signature.py
suprsend/subscriber.py
suprsend/subscriber_helper.py
suprsend/subscriber_list.py
suprsend/subscribers_bulk.py
suprsend/tenant.py
suprsend/user_edit.py
suprsend/user_edit_internal_helper.py
suprsend/users_api.py
suprsend/users_edit_bulk.py
suprsend/utils.py
suprsend/version.py
suprsend/workflow.py
suprsend/workflow_api.py
suprsend/workflow_request.py
suprsend/workflow_trigger_bulk.py
suprsend/workflows_bulk.py
suprsend/request_json/event.json
suprsend/request_json/list_broadcast.json
suprsend/request_json/workflow.json
suprsend/request_json/workflow_trigger.json
suprsend_py_sdk-0.16.0.dist-info/licenses/LICENSE
suprsend_py_sdk-0.16.0.dist-info/METADATA
suprsend_py_sdk-0.16.0.dist-info/WHEEL
suprsend_py_sdk-0.16.0.dist-info/top_level.txt
suprsend_py_sdk-0.16.0.dist-info/RECORD
