Metadata-Version: 2.4
Name: suprsend-py-sdk
Version: 0.16.0
Summary: Suprsend library for Python
Home-page: https://github.com/suprsend/suprsend-py-sdk
Author: Suprsend
Author-email: sanjeev@suprsend.com
Project-URL: Bug Tracker, https://github.com/suprsend/suprsend-py-sdk/issues
Classifier: Programming Language :: Python :: 3
Classifier: Programming Language :: Python :: 3.9
Classifier: Programming Language :: Python :: 3.10
Classifier: Programming Language :: Python :: 3.11
Classifier: Programming Language :: Python :: 3.12
Classifier: Programming Language :: Python :: 3.13
Requires-Python: >=3.9
License-File: LICENSE
Requires-Dist: jsonschema
Requires-Dist: requests
Requires-Dist: python-magic
Dynamic: license-file
